mkdocs_gentags/__init__.py
mkdocs_gentags/config.py
mkdocs_gentags/plugin.py
mkdocs_gentags/py.typed
mkdocs_gentags-0.0.1.dist-info/METADATA
mkdocs_gentags-0.0.1.dist-info/WHEEL
mkdocs_gentags-0.0.1.dist-info/entry_points.txt
mkdocs_gentags-0.0.1.dist-info/licenses/LICENSE
mkdocs_gentags-0.0.1.dist-info/RECORD
