Metadata-Version: 2.3
Name: mkdocs-gentags
Version: 0.0.1
Summary: A mkdocs plugin to generate tag files based on metadata information.
Project-URL: Documentation, https://github.com/georgeyk/mkdocs-gentags/#README.md
Project-URL: Issues, https://github.com/georgeyk/mkdocs-gentags/issues
Project-URL: Source, https://github.com/georgeyk/mkdocs-gentags
Author-email: "George Y. Kussumoto" <georgeyk.dev@gmail.com>
License-Expression: MIT
License-File: LICENSE
Keywords: mkdocs,mkdocs-plugin,plugin,tag,tagging,tags
Classifier: Development Status :: 4 - Beta
Classifier: Programming Language :: Python
Classifier: Programming Language :: Python :: 3.9
Classifier: Programming Language :: Python :: 3.10
Classifier: Programming Language :: Python :: 3.11
Classifier: Programming Language :: Python :: 3.12
Classifier: Programming Language :: Python :: Implementation :: CPython
Classifier: Programming Language :: Python :: Implementation :: PyPy
Requires-Python: >=3.9
Requires-Dist: mkdocs<2,>=1.6
